aws_secrets_vault/__init__.py
aws_secrets_vault/__init__.pyi
aws_secrets_vault/__main__.py
aws_secrets_vault/__main__.pyi
aws_secrets_vault-1.0.4.dist-info/METADATA
aws_secrets_vault-1.0.4.dist-info/WHEEL
aws_secrets_vault-1.0.4.dist-info/RECORD
